blazarnova/__init__.py
blazarnova/i18n.py
blazarnova/scheduler/__init__.py
blazarnova/scheduler/filters/__init__.py
blazarnova/scheduler/filters/blazar_filter.py
blazarnova/tests/__init__.py
blazarnova/tests/scheduler/__init__.py
blazarnova/tests/scheduler/filters/__init__.py
blazarnova/tests/scheduler/filters/test_blazar_filter.py
blazar_nova-8.0.0.dist-info/AUTHORS
blazar_nova-8.0.0.dist-info/LICENSE
blazar_nova-8.0.0.dist-info/METADATA
blazar_nova-8.0.0.dist-info/WHEEL
blazar_nova-8.0.0.dist-info/pbr.json
blazar_nova-8.0.0.dist-info/top_level.txt
blazar_nova-8.0.0.dist-info/RECORD
