Metadata-Version: 2.1
Name: blazar-nova
Version: 8.0.0
Summary: Nova related filters and extensions for Blazar
Home-page: https://launchpad.net/blazar
Author: OpenStack
Author-email: openstack-discuss@lists.openstack.org
License: Apache Software License
Classifier: Programming Language :: Python
Classifier: Programming Language :: Python :: Implementation :: CPython
Classifier: Programming Language :: Python :: 3 :: Only
Classifier: Programming Language :: Python :: 3
Classifier: Programming Language :: Python :: 3.10
Classifier: Programming Language :: Python :: 3.11
Classifier: Programming Language :: Python :: 3.12
Classifier: Environment :: OpenStack
Classifier: Development Status :: 3 - Alpha
Classifier: Framework :: Setuptools Plugin
Classifier: Intended Audience :: Information Technology
Classifier: Intended Audience :: System Administrators
Classifier: License :: OSI Approved :: Apache Software License
Classifier: Operating System :: POSIX :: Linux
Requires-Python: >=3.10
License-File: LICENSE
License-File: AUTHORS
Requires-Dist: pbr >=5.8.0
Requires-Dist: oslo.config >=8.6.0
Requires-Dist: oslo.i18n >=5.1.0
Requires-Dist: oslo.log >=4.6.1
